nginx_sqlize/__init__.py
nginx_sqlize/core.py
nginx_sqlize/main.py
nginx_sqlize/queries.py
nginx_sqlize-0.2.2.dist-info/METADATA
nginx_sqlize-0.2.2.dist-info/WHEEL
nginx_sqlize-0.2.2.dist-info/entry_points.txt
nginx_sqlize-0.2.2.dist-info/licenses/LICENSE
nginx_sqlize-0.2.2.dist-info/RECORD
