Metadata-Version: 2.4
Name: nginx-sqlize
Version: 0.2.2
Summary: A tool to import Nginx logs into SQLite for easy querying.
Project-URL: Homepage, https://github.com/fidacura/nginx-sqlize
Project-URL: Documentation, https://github.com/fidacura/nginx-sqlize#readme
Project-URL: Repository, https://github.com/fidacura/nginx-sqlize.git
Project-URL: Issues, https://github.com/fidacura/nginx-sqlize/issues
Author-email: fidacura <hey@fidacura.net>
License-Expression: GPL-2.0-only
License-File: LICENSE
Keywords: analytics,cli,logs,nginx,sqlite
Classifier: Development Status :: 5 - Production/Stable
Classifier: Environment :: Console
Classifier: Intended Audience :: System Administrators
Classifier: License :: OSI Approved :: GNU General Public License v2 (GPLv2)
Classifier: Programming Language :: Python :: 3
Classifier: Programming Language :: Python :: 3.9
Classifier: Programming Language :: Python :: 3.10
Classifier: Programming Language :: Python :: 3.11
Classifier: Programming Language :: Python :: 3.12
Classifier: Topic :: System :: Logging
Classifier: Topic :: System :: Systems Administration
Requires-Python: >=3.9
Requires-Dist: loguru>=0.7.0
Requires-Dist: pydantic>=2.0.0
Requires-Dist: rich>=13.0.0
Requires-Dist: typer[all]>=0.9.0
Provides-Extra: dev
Requires-Dist: black>=23.0.0; extra == 'dev'
Requires-Dist: mypy>=1.5.0; extra == 'dev'
Requires-Dist: pre-commit>=3.4.0; extra == 'dev'
Requires-Dist: pytest-cov>=4.1.0; extra == 'dev'
Requires-Dist: pytest>=7.4.0; extra == 'dev'
Requires-Dist: ruff>=0.1.0; extra == 'dev'
Provides-Extra: test
Requires-Dist: pytest-cov>=4.1.0; extra == 'test'
Requires-Dist: pytest-mock>=3.11.0; extra == 'test'
Requires-Dist: pytest>=7.4.0; extra == 'test'
